aamras/__init__.py
aamras/__version__.py
aamras/driver/__init__.py
aamras/driver/cookies.py
aamras/driver/driver.py
aamras/driver/element.py
aamras/driver/factory.py
aamras/driver/traverser.py
aamras/util/__init__.py
aamras/util/file_.py
aamras/util/logger.py
aamras-0.0.3.data/data/LICENSE
aamras-0.0.3.dist-info/LICENSE
aamras-0.0.3.dist-info/METADATA
aamras-0.0.3.dist-info/WHEEL
aamras-0.0.3.dist-info/top_level.txt
aamras-0.0.3.dist-info/RECORD
