Metadata-Version: 2.1
Name: aamras
Version: 0.0.3
Summary: Library for headless browser manipulation
Home-page: https://github.com/allekmott/aamras
Author: Allek Mott
Author-email: allekmott@gmail.com
License: GPLv3
Project-URL: Documentation, https://aamras.readthedocs.io/
Project-URL: Source, https://github.com/allekmott/aamras
Platform: UNKNOWN
Classifier: Development Status :: 3 - Alpha
Classifier: Intended Audience :: Developers
Classifier: Natural Language :: English
Classifier: License :: OSI Approved :: GNU General Public License v3 (GPLv3)
Classifier: Operating System :: MacOS :: MacOS X
Classifier: Operating System :: POSIX :: Linux
Classifier: Programming Language :: Python
Classifier: Programming Language :: Python :: 3.6
Classifier: Programming Language :: Python :: 3.7
Classifier: Programming Language :: Python :: 3.8
Classifier: Topic :: Software Development :: Libraries
Requires-Python: >=3.6
Requires-Dist: selenium
Provides-Extra: dev
Requires-Dist: flake8 ; extra == 'dev'
Requires-Dist: mypy ; extra == 'dev'
Requires-Dist: pytest ; extra == 'dev'
Requires-Dist: pytest-cov ; extra == 'dev'
Requires-Dist: pipenv-setup ; extra == 'dev'
Requires-Dist: sphinx ; extra == 'dev'
